parallelbam/__init__.py
parallelbam/parallelbam.py
parallelbam-0.0.19.data/scripts/mergeBAMs.sh
parallelbam-0.0.19.data/scripts/splitBAM.sh
parallelbam-0.0.19.dist-info/LICENSE
parallelbam-0.0.19.dist-info/METADATA
parallelbam-0.0.19.dist-info/WHEEL
parallelbam-0.0.19.dist-info/top_level.txt
parallelbam-0.0.19.dist-info/RECORD
